{"_id":{"$oid":"5ecbf9de7ab3772f0edaceff"},"datetime":"20200526000118","message":"Camera 1 not avaliable"}
{"_id":{"$oid":"5ecbff63f939483e8a2f4d27"},"datetime":"20200526002451","message":"Camera 2 not avaliable"}
{"_id":{"$oid":"5ecc058303c5611600eaf692"},"datetime":"20200526005059","message":"Camera 3 not avaliable"}
{"_id":{"$oid":"5ecc0b82bbdf863186eedc01"},"datetime":"20200526011634","message":"Camera 2 not avaliable"}
{"_id":{"$oid":"5ecc0bb844585f716c29c588"},"datetime":"20200526011728","message":"Camera 2 not avaliable"}
{"_id":{"$oid":"5ecc0ca07f5dd10f252e0ced"},"datetime":"20200526012120","message":"Camera 2 not avaliable"}
{"_id":{"$oid":"5ecc0cc0324c0a56467e50cf"},"datetime":"20200526012152","message":"Camera 2 not avaliable"}
{"_id":{"$oid":"5ecc156ebc8961ff348eca1d"},"datetime":"20200526015854","message":"Camera 2 not avaliable"}
{"_id":{"$oid":"5ecc1576059f740dda454387"},"datetime":"20200526015902","message":"Camera 4 not avaliable"}
{"_id":{"$oid":"5ecc27b09780232f832da476"},"datetime":"20200526031648","message":"Camera 2 not avaliable"}
{"_id":{"$oid":"5ecc37d3ee9a1f694583a881"},"datetime":"20200526042539","message":"Camera 2 not avaliable"}
{"_id":{"$oid":"5ecc37f54864cc9e8883decc"},"datetime":"20200526042613","message":"Camera 2 not avaliable"}
{"_id":{"$oid":"5ecc7dc3c582d98735b5036f"},"datetime":"20200526092403","message":"Camera 2 not avaliable"}
{"_id":{"$oid":"5ecc7e3173c7d560a949b88b"},"datetime":"20200526092553","message":"Camera 2 not avaliable"}
{"_id":{"$oid":"5eccbb167348e75e63c73b5f"},"datetime":"20200526134542","message":"Camera 2 not avaliable"}
{"_id":{"$oid":"5ecd024a5be3e69f2de25b81"},"datetime":"20200526184930","message":"Camera 2 not avaliable"}
{"_id":{"$oid":"5ecd0c713c0f6bf350c3b57e"},"datetime":"20200526193249","message":"Camera 2 not avaliable"}
{"_id":{"$oid":"5ecd0d09679b0a119d36cc71"},"datetime":"20200526193521","message":"Camera 2 not avaliable"}
{"_id":{"$oid":"5ecd0d4bfc9189c2e4714748"},"datetime":"20200526193627","message":"Camera 2 not avaliable"}
{"_id":{"$oid":"5ecd120945f10acbee1886ed"},"datetime":"20200526195641","message":"Camera 2 not avaliable"}
{"_id":{"$oid":"5ecd140e93fd27ab46f94a4e"},"datetime":"20200526200518","message":"Camera 2 not avaliable"}
{"_id":{"$oid":"5ecd17c992a6fedb7f5cc89f"},"datetime":"20200526202113","message":"Camera 2 not avaliable"}
{"_id":{"$oid":"5ecd195f55b7f8b87875194a"},"datetime":"20200526202759","message":"Camera 2 not avaliable"}
{"_id":{"$oid":"5ecd19b690b01bccbf5544d2"},"datetime":"20200526202926","message":"Camera 2 not avaliable"}
{"_id":{"$oid":"5ecd1e847e5cae973e4f4875"},"datetime":"20200526204956","message":"Camera 2 not avaliable"}
{"_id":{"$oid":"5ecd220301300f982e715452"},"datetime":"20200526210451","message":"Camera 2 not avaliable"}
{"_id":{"$oid":"5ecd2243a30685cf02f61323"},"datetime":"20200526210555","message":"Camera 2 not avaliable"}
{"_id":{"$oid":"5ecd251e4c277f64afcebf78"},"datetime":"20200526211806","message":"Camera 2 not avaliable"}
{"_id":{"$oid":"5ecd25b5c9e3095c06cd88da"},"datetime":"20200526212037","message":"Camera 2 not avaliable"}
{"_id":{"$oid":"5ecd294f5089def6bb11ea2d"},"datetime":"20200526213559","message":"Camera 2 not avaliable"}
{"_id":{"$oid":"5ecd2a54a493c5d0e640701c"},"datetime":"20200526214020","message":"Camera 2 not avaliable"}
{"_id":{"$oid":"5ecd2e8c2a4c0f8142c2e9a6"},"datetime":"20200526215820","message":"Camera 2 not avaliable"}
{"_id":{"$oid":"5ecd306f90fdf3ac47bccbaa"},"datetime":"20200526220623","message":"Camera 2 not avaliable"}
{"_id":{"$oid":"5ecd316fbe13e41f64bbcabb"},"datetime":"20200526221039","message":"Camera 2 not avaliable"}
{"_id":{"$oid":"5ecd3276a08abe92f24e04e2"},"datetime":"20200526221502","message":"Camera 2 not avaliable"}
{"_id":{"$oid":"5ecd3485a3ed2360e9106068"},"datetime":"20200526222349","message":"Camera 2 not avaliable"}
{"_id":{"$oid":"5ecd3780837cfc7a12fd1c7a"},"datetime":"20200526223632","message":"Camera 2 not avaliable"}
{"_id":{"$oid":"5ecd3a33313b7f63a23643de"},"datetime":"20200526224803","message":"Camera 2 not avaliable"}
{"_id":{"$oid":"5ecd3c869c2846bd4dfc01bb"},"datetime":"20200526225758","message":"Camera 2 not avaliable"}
{"_id":{"$oid":"5ecd3e758d8b77cfa24ba509"},"datetime":"20200526230613","message":"Camera 1 not avaliable"}
{"_id":{"$oid":"5ecd3f0db3df82b9c983d322"},"datetime":"20200526230845","message":"Camera 2 not avaliable"}
{"_id":{"$oid":"5ecd3fd7c6aede9847389bde"},"datetime":"20200526231207","message":"Camera 2 not avaliable"}
{"_id":{"$oid":"5ecd405f094f8de98580c5fb"},"datetime":"20200526231423","message":"Camera 2 not avaliable"}
{"_id":{"$oid":"5ecd41a4ce52d9931f7792d9"},"datetime":"20200526231948","message":"Camera 2 not avaliable"}
{"_id":{"$oid":"5ecd43ca6090e16ce38b7b9f"},"datetime":"20200526232858","message":"Camera 2 not avaliable"}
{"_id":{"$oid":"5ecd453d45e8f1e092c095f3"},"datetime":"20200526233509","message":"Camera 2 not avaliable"}
{"_id":{"$oid":"5ecd45429274446c161919db"},"datetime":"20200526233514","message":"Camera 1 not avaliable"}
{"_id":{"$oid":"5ecd459d9abdb70a57a4f054"},"datetime":"20200526233645","message":"Camera 3 not avaliable"}
{"_id":{"$oid":"5ecd45d5da9a62cbe66f56c5"},"datetime":"20200526233741","message":"Camera 1 not avaliable"}
{"_id":{"$oid":"5ecd46af83fe52053f9c3f0b"},"datetime":"20200526234119","message":"Camera 4 not avaliable"}
{"_id":{"$oid":"5ecd47736b844ace6c8ff2aa"},"datetime":"20200526234435","message":"Camera 2 not avaliable"}
{"_id":{"$oid":"5ecd47f8dba3c20e4121a3d0"},"datetime":"20200526234648","message":"Camera 2 not avaliable"}
{"_id":{"$oid":"5ecd48461e6058b33fce7721"},"datetime":"20200526234806","message":"Camera 2 not avaliable"}
{"_id":{"$oid":"5ecd48d36e4e221f4e69ea3a"},"datetime":"20200526235027","message":"Camera 2 not avaliable"}
{"_id":{"$oid":"5ecd4920ffdf5a123759f738"},"datetime":"20200526235144","message":"Camera 2 not avaliable"}
{"_id":{"$oid":"5ecd4a3043dab40dc77cdf01"},"datetime":"20200526235616","message":"Camera 2 not avaliable"}
{"_id":{"$oid":"5ecd4a8e2ba6aae58b27dfcd"},"datetime":"20200526235750","message":"Camera 1 not avaliable"}
{"_id":{"$oid":"5ecd4abce2ff0d6abed5bd21"},"datetime":"20200526235836","message":"Camera 2 not avaliable"}
