{"_id":{"$oid":"5f459b77ae80396a4edddb52"},"id":"1976613","checkin":"06:14","checkindatetime":"20200826061459","checkinEmotion":{"gender":"female","age":62.0,"emotion":{"anger":0.0,"contempt":0.002,"disgust":0.0,"fear":0.0,"happiness":0.001,"neutral":0.974,"sadness":0.022,"surprise":0.001}},"checkinEmo":"sadness","checkinImageCrop":"2020-08-26-3-061459200-crop.jpg","camerain":3,"checkout":"15:56","checkoutEmotion":{"gender":"female","age":48,"emotion":{"anger":0,"contempt":0,"disgust":0,"fear":0,"happiness":0,"neutral":1,"sadness":0,"surprise":0}},"checkoutEmo":"neutral","checkoutImageCrop":"2020-08-26-4-155622560-crop.jpg","cameraout":4,"checkoutdatetime":"20200826155622"}
{"_id":{"$oid":"5f45a086ae80396a4eddfb2e"},"id":"2075533","checkin":"06:36","checkindatetime":"20200826063633","checkinEmotion":{"gender":"female","age":39,"emotion":{"anger":0,"contempt":0,"disgust":0,"fear":0,"happiness":0,"neutral":1,"sadness":0,"surprise":0}},"checkinEmo":"neutral","checkinImageCrop":"2020-08-26-3-06363300-crop.jpg","camerain":3,"checkout":"15:55","checkoutEmotion":{"gender":"female","age":39,"emotion":{"anger":0,"contempt":0,"disgust":0,"fear":0,"happiness":0,"neutral":1,"sadness":0,"surprise":0}},"checkoutEmo":"neutral","checkoutImageCrop":"2020-08-26-2-155520160-crop.jpg","cameraout":2,"checkoutdatetime":"20200826155520"}
{"_id":{"$oid":"5f45a601ae80396a4ede1d22"},"id":"2261926","checkin":"06:59","checkindatetime":"20200826065957","checkinEmotion":{"gender":"male","age":27.0,"emotion":{"anger":0.002,"contempt":0.337,"disgust":0.0,"fear":0.0,"happiness":0.0,"neutral":0.654,"sadness":0.006,"surprise":0.0}},"checkinEmo":"contempt","checkinImageCrop":"2020-08-26-3-06595700-crop.jpg","camerain":3,"checkout":"17:34","checkoutEmotion":{"gender":"male","age":31,"emotion":{"anger":0,"contempt":0,"disgust":0,"fear":0,"happiness":0,"neutral":1,"sadness":0,"surprise":0}},"checkoutEmo":"neutral","checkoutImageCrop":"2020-08-26-4-173406240-crop.jpg","cameraout":4,"checkoutdatetime":"20200826173406"}
{"_id":{"$oid":"5f45a82dae80396a4ede2ae9"},"id":"2210116","checkin":"06:42","checkindatetime":"20200826064217","checkinEmotion":{"gender":"male","age":27,"emotion":{"anger":0,"contempt":0,"disgust":0,"fear":0,"happiness":0,"neutral":1,"sadness":0,"surprise":0}},"checkinEmo":"neutral","checkinImageCrop":"2020-08-26-3-064217400-crop.jpg","camerain":3,"checkout":"17:11","checkoutEmotion":{"gender":"male","age":37.0,"emotion":{"anger":0.001,"contempt":0.003,"disgust":0.0,"fear":0.0,"happiness":0.004,"neutral":0.985,"sadness":0.007,"surprise":0.0}},"checkoutEmo":"sadness","checkoutImageCrop":"2020-08-26-4-171122520-crop.jpg","cameraout":4,"checkoutdatetime":"20200826171122"}
{"_id":{"$oid":"5f45adafae80396a4ede4e96"},"id":"2220206","checkin":"07:32","checkindatetime":"20200826073241","checkinEmotion":{"gender":"female","age":29,"emotion":{"anger":0,"contempt":0,"disgust":0,"fear":0,"happiness":0,"neutral":1,"sadness":0,"surprise":0}},"checkinEmo":"neutral","checkinImageCrop":"2020-08-26-3-073241200-crop.jpg","camerain":3,"checkout":"14:44","checkoutEmotion":{"gender":"female","age":29,"emotion":{"anger":0,"contempt":0,"disgust":0,"fear":0,"happiness":0,"neutral":1,"sadness":0,"surprise":0}},"checkoutEmo":"neutral","checkoutImageCrop":"2020-08-26-4-144413560-crop.jpg","cameraout":4,"checkoutdatetime":"20200826144413"}
{"_id":{"$oid":"5f45adf1ae80396a4ede5052"},"id":"2262824","checkin":"07:33","checkindatetime":"20200826073347","checkinEmotion":{"gender":"male","age":28,"emotion":{"anger":0,"contempt":0,"disgust":0,"fear":0,"happiness":0,"neutral":1,"sadness":0,"surprise":0}},"checkinEmo":"neutral","checkinImageCrop":"2020-08-26-3-073347200-crop.jpg","camerain":3,"checkout":"15:54","checkoutEmotion":{"gender":"male","age":28.0,"emotion":{"anger":0.002,"contempt":0.0,"disgust":0.0,"fear":0.0,"happiness":0.005,"neutral":0.981,"sadness":0.012,"surprise":0.0}},"checkoutEmo":"sadness","checkoutImageCrop":"2020-08-26-4-155430360-crop.jpg","cameraout":4,"checkoutdatetime":"20200826155430"}
{"_id":{"$oid":"5f45aeb3ae80396a4ede5574"},"id":"2185224","checkin":"07:37","checkindatetime":"20200826073704","checkinEmotion":{"gender":"female","age":33.0,"emotion":{"anger":0.0,"contempt":0.001,"disgust":0.0,"fear":0.0,"happiness":0.004,"neutral":0.963,"sadness":0.031,"surprise":0.0}},"checkinEmo":"sadness","checkinImageCrop":"2020-08-26-3-073704400-crop.jpg","camerain":3,"checkout":"15:23","checkoutEmotion":{"gender":"female","age":33,"emotion":{"anger":0,"contempt":0,"disgust":0,"fear":0,"happiness":0,"neutral":1,"sadness":0,"surprise":0}},"checkoutEmo":"neutral","checkoutImageCrop":"2020-08-26-4-152329520-crop.jpg","cameraout":4,"checkoutdatetime":"20200826152329"}
{"_id":{"$oid":"5f45af5eae80396a4ede59c9"},"id":"1576001","checkin":"07:39","checkindatetime":"20200826073953","checkinEmotion":{"gender":"female","age":47.0,"emotion":{"anger":0.002,"contempt":0.012,"disgust":0.001,"fear":0.0,"happiness":0.122,"neutral":0.839,"sadness":0.023,"surprise":0.0}},"checkinEmo":"happiness","checkinImageCrop":"2020-08-26-3-07395300-crop.jpg","camerain":3,"checkout":"14:31","checkoutEmotion":{"gender":"female","age":46,"emotion":{"anger":0,"contempt":0,"disgust":0,"fear":0,"happiness":0,"neutral":1,"sadness":0,"surprise":0}},"checkoutEmo":"neutral","checkoutImageCrop":"2020-08-26-4-143156280-crop.jpg","cameraout":4,"checkoutdatetime":"20200826143156"}
{"_id":{"$oid":"5f45b19bae80396a4ede68a7"},"id":"2311622","checkin":"07:49","checkindatetime":"20200826074925","checkinEmotion":{"gender":"female","age":27,"emotion":{"anger":0,"contempt":0,"disgust":0,"fear":0,"happiness":0,"neutral":1,"sadness":0,"surprise":0}},"checkinEmo":"neutral","checkinImageCrop":"2020-08-26-3-074925200-crop.jpg","camerain":3,"checkout":"17:35","checkoutEmotion":{"gender":"female","age":27,"emotion":{"anger":0,"contempt":0,"disgust":0,"fear":0,"happiness":0,"neutral":1,"sadness":0,"surprise":0}},"checkoutEmo":"neutral","checkoutImageCrop":"2020-08-26-4-17354440-crop.jpg","cameraout":4,"checkoutdatetime":"20200826173544"}
{"_id":{"$oid":"5f45b2e8ae80396a4ede71b9"},"id":"1559425","checkin":"07:54","checkindatetime":"20200826075459","checkinEmotion":{"gender":"female","age":51,"emotion":{"anger":0,"contempt":0,"disgust":0,"fear":0,"happiness":0,"neutral":1,"sadness":0,"surprise":0}},"checkinEmo":"neutral","checkinImageCrop":"2020-08-26-3-075459200-crop.jpg","camerain":3,"checkout":"14:15","checkoutEmotion":{"gender":"female","age":55.0,"emotion":{"anger":0.006,"contempt":0.001,"disgust":0.0,"fear":0.0,"happiness":0.0,"neutral":0.984,"sadness":0.009,"surprise":0.0}},"checkoutEmo":"sadness","checkoutImageCrop":"2020-08-26-4-141518120-crop.jpg","cameraout":4,"checkoutdatetime":"20200826141518"}
{"_id":{"$oid":"5f45b2eeae80396a4ede71ef"},"id":"2067627","checkin":"07:55","checkindatetime":"20200826075507","checkinEmotion":{"gender":"female","age":49.0,"emotion":{"anger":0.002,"contempt":0.165,"disgust":0.002,"fear":0.001,"happiness":0.114,"neutral":0.69,"sadness":0.025,"surprise":0.001}},"checkinEmo":"contempt","checkinImageCrop":"2020-08-26-3-075507400-crop.jpg","camerain":3,"checkout":"15:21","checkoutEmotion":{"gender":"female","age":51.0,"emotion":{"anger":0.002,"contempt":0.001,"disgust":0.0,"fear":0.0,"happiness":0.0,"neutral":0.942,"sadness":0.055,"surprise":0.0}},"checkoutEmo":"sadness","checkoutImageCrop":"2020-08-26-4-152109120-crop.jpg","cameraout":4,"checkoutdatetime":"20200826152109"}
{"_id":{"$oid":"5f45b38fae80396a4ede7617"},"id":"1976807","checkin":"07:57","checkindatetime":"20200826075748","checkinEmotion":{"gender":"female","age":38.0,"emotion":{"anger":0.018,"contempt":0.032,"disgust":0.001,"fear":0.001,"happiness":0.037,"neutral":0.885,"sadness":0.026,"surprise":0.0}},"checkinEmo":"happiness","checkinImageCrop":"2020-08-26-3-07574800-crop.jpg","camerain":3,"checkout":"16:05","checkoutEmotion":{"gender":"female","age":45,"emotion":{"anger":0,"contempt":0,"disgust":0,"fear":0,"happiness":0,"neutral":1,"sadness":0,"surprise":0}},"checkoutEmo":"neutral","checkoutImageCrop":"2020-08-26-4-160503321-crop.jpg","cameraout":4,"checkoutdatetime":"20200826160503"}
{"_id":{"$oid":"5f45b3a8ae80396a4ede76d5"},"id":"2237007","checkin":"07:58","checkindatetime":"20200826075813","checkinEmotion":{"gender":"male","age":32.0,"emotion":{"anger":0.001,"contempt":0.001,"disgust":0.0,"fear":0.0,"happiness":0.001,"neutral":0.957,"sadness":0.04,"surprise":0.0}},"checkinEmo":"sadness","checkinImageCrop":"2020-08-26-3-075813200-crop.jpg","camerain":3,"checkout":"15:37","checkoutEmotion":{"gender":"male","age":35.0,"emotion":{"anger":0.0,"contempt":0.0,"disgust":0.0,"fear":0.0,"happiness":0.003,"neutral":0.152,"sadness":0.843,"surprise":0.0}},"checkoutEmo":"sadness","checkoutImageCrop":"2020-08-26-4-153738400-crop.jpg","cameraout":4,"checkoutdatetime":"20200826153738"}
{"_id":{"$oid":"5f45b425ae80396a4ede7a45"},"id":"2170413","checkin":"08:00","checkindatetime":"20200826080017","checkinEmotion":{"gender":"female","age":41.0,"emotion":{"anger":0.001,"contempt":0.062,"disgust":0.001,"fear":0.001,"happiness":0.008,"neutral":0.704,"sadness":0.223,"surprise":0.0}},"checkinEmo":"sadness","checkinImageCrop":"2020-08-26-3-080017400-crop.jpg","camerain":3,"checkout":"17:24","checkoutEmotion":{"gender":"female","age":32.0,"emotion":{"anger":0.0,"contempt":0.008,"disgust":0.0,"fear":0.0,"happiness":0.231,"neutral":0.758,"sadness":0.003,"surprise":0.0}},"checkoutEmo":"happiness","checkoutImageCrop":"2020-08-26-2-17240200-crop.jpg","cameraout":2,"checkoutdatetime":"20200826172402"}
{"_id":{"$oid":"5f45b581ae80396a4ede8363"},"id":"2144026","checkin":"08:06","checkindatetime":"20200826080605","checkinEmotion":{"gender":"male","age":56.0,"emotion":{"anger":0.0,"contempt":0.005,"disgust":0.0,"fear":0.0,"happiness":0.752,"neutral":0.238,"sadness":0.004,"surprise":0.001}},"checkinEmo":"happiness","checkinImageCrop":"2020-08-26-3-080605200-crop.jpg","camerain":3,"checkout":"10:49","checkoutEmotion":{"gender":"male","age":47.0,"emotion":{"anger":0.0,"contempt":0.0,"disgust":0.0,"fear":0.0,"happiness":0.0,"neutral":0.982,"sadness":0.017,"surprise":0.001}},"checkoutEmo":"sadness","checkoutImageCrop":"2020-08-26-2-104917440-crop.jpg","cameraout":2,"checkoutdatetime":"20200826104917"}
{"_id":{"$oid":"5f45b6cfae80396a4ede8be5"},"id":"2163502","checkin":"08:11","checkindatetime":"20200826081139","checkinEmotion":{"gender":"male","age":34.0,"emotion":{"anger":0.007,"contempt":0.005,"disgust":0.0,"fear":0.0,"happiness":0.002,"neutral":0.985,"sadness":0.001,"surprise":0.0}},"checkinEmo":"anger","checkinImageCrop":"2020-08-26-3-081139200-crop.jpg","camerain":3,"checkout":"16:06","checkoutEmotion":{"gender":"male","age":29.0,"emotion":{"anger":0.002,"contempt":0.003,"disgust":0.0,"fear":0.0,"happiness":0.001,"neutral":0.972,"sadness":0.023,"surprise":0.0}},"checkoutEmo":"sadness","checkoutImageCrop":"2020-08-26-4-16064480-crop.jpg","cameraout":4,"checkoutdatetime":"20200826160644"}
{"_id":{"$oid":"5f45b884ae80396a4ede969d"},"id":"2222718","checkin":"07:16","checkindatetime":"20200826071612","checkinEmotion":{"gender":"male","age":30,"emotion":{"anger":0,"contempt":0,"disgust":0,"fear":0,"happiness":0,"neutral":1,"sadness":0,"surprise":0}},"checkinEmo":"neutral","checkinImageCrop":"2020-08-26-3-071612400-crop.jpg","camerain":3,"checkout":"16:06","checkoutEmotion":{"gender":"male","age":35.0,"emotion":{"anger":0.0,"contempt":0.0,"disgust":0.0,"fear":0.0,"happiness":1.0,"neutral":0.0,"sadness":0.0,"surprise":0.0}},"checkoutEmo":"happiness","checkoutImageCrop":"2020-08-26-4-160610560-crop.jpg","cameraout":4,"checkoutdatetime":"20200826160610"}
{"_id":{"$oid":"5f45b947ae80396a4ede9b7d"},"id":"1674425","checkin":"08:22","checkindatetime":"20200826082211","checkinEmotion":{"gender":"female","age":39.0,"emotion":{"anger":0.0,"contempt":0.0,"disgust":0.0,"fear":0.0,"happiness":0.0,"neutral":0.988,"sadness":0.011,"surprise":0.0}},"checkinEmo":"sadness","checkinImageCrop":"2020-08-26-3-08221100-crop.jpg","camerain":3,"checkout":"15:22","checkoutEmotion":{"gender":"female","age":60.0,"emotion":{"anger":0.0,"contempt":0.0,"disgust":0.0,"fear":0.0,"happiness":0.0,"neutral":0.976,"sadness":0.023,"surprise":0.0}},"checkoutEmo":"sadness","checkoutImageCrop":"2020-08-26-2-15225640-crop.jpg","cameraout":2,"checkoutdatetime":"20200826152256"}
{"_id":{"$oid":"5f45bad4ae80396a4edea595"},"id":"1925325","checkin":"08:28","checkindatetime":"20200826082848","checkinEmotion":{"gender":"female","age":44.0,"emotion":{"anger":0.009,"contempt":0.001,"disgust":0.005,"fear":0.09,"happiness":0.026,"neutral":0.489,"sadness":0.321,"surprise":0.059}},"checkinEmo":"sadness","checkinImageCrop":"2020-08-26-3-082848200-crop.jpg","camerain":3,"checkout":"16:10","checkoutEmotion":{"gender":"female","age":56.0,"emotion":{"anger":0.002,"contempt":0.001,"disgust":0.0,"fear":0.0,"happiness":0.018,"neutral":0.935,"sadness":0.044,"surprise":0.0}},"checkoutEmo":"sadness","checkoutImageCrop":"2020-08-26-4-161011120-crop.jpg","cameraout":4,"checkoutdatetime":"20200826161011"}
{"_id":{"$oid":"5f45bbe1ae80396a4edeac78"},"id":"2506425","checkin":"08:33","checkindatetime":"20200826083318","checkinEmotion":{"gender":"male","age":30.0,"emotion":{"anger":0.005,"contempt":0.001,"disgust":0.0,"fear":0.0,"happiness":0.0,"neutral":0.985,"sadness":0.007,"surprise":0.0}},"checkinEmo":"sadness","checkinImageCrop":"2020-08-26-3-08331800-crop.jpg","camerain":3,"checkout":"17:21","checkoutEmotion":{"gender":"male","age":27.0,"emotion":{"anger":0.0,"contempt":0.002,"disgust":0.0,"fear":0.0,"happiness":0.0,"neutral":0.817,"sadness":0.181,"surprise":0.0}},"checkoutEmo":"sadness","checkoutImageCrop":"2020-08-26-2-172134240-crop.jpg","cameraout":2,"checkoutdatetime":"20200826172134"}
{"_id":{"$oid":"5f45bc01ae80396a4edead63"},"id":"2184520","checkin":"08:33","checkindatetime":"20200826083349","checkinEmotion":{"gender":"female","age":41.0,"emotion":{"anger":0.0,"contempt":0.0,"disgust":0.0,"fear":0.0,"happiness":1.0,"neutral":0.0,"sadness":0.0,"surprise":0.0}},"checkinEmo":"happiness","checkinImageCrop":"2020-08-26-3-083349400-crop.jpg","camerain":3,"checkout":"12:42","checkoutEmotion":{"gender":"female","age":33,"emotion":{"anger":0,"contempt":0,"disgust":0,"fear":0,"happiness":0,"neutral":1,"sadness":0,"surprise":0}},"checkoutEmo":"neutral","checkoutImageCrop":"2020-08-26-4-12423080-crop.jpg","cameraout":0,"checkoutdatetime":"20200826124230"}
{"_id":{"$oid":"5f45bc93ae80396a4edeb0ff"},"id":"2517025","checkin":"08:36","checkindatetime":"20200826083611","checkinEmotion":{"gender":"male","age":34.0,"emotion":{"anger":0.0,"contempt":0.0,"disgust":0.0,"fear":0.0,"happiness":0.0,"neutral":0.956,"sadness":0.0,"surprise":0.044}},"checkinEmo":"surprise","checkinImageCrop":"2020-08-26-3-083611400-crop.jpg","camerain":3,"checkout":"12:40","checkoutEmotion":{"gender":"male","age":28,"emotion":{"anger":0,"contempt":0,"disgust":0,"fear":0,"happiness":0,"neutral":1,"sadness":0,"surprise":0}},"checkoutEmo":"neutral","checkoutImageCrop":"2020-08-26-4-124046360-crop.jpg","cameraout":4,"checkoutdatetime":"20200826124046"}
{"_id":{"$oid":"5f45d45dae80396a4edf4432"},"id":"2262727","checkin":"10:17","checkindatetime":"20200826101743","checkinEmotion":{"gender":"male","age":38.0,"emotion":{"anger":0.0,"contempt":0.001,"disgust":0.0,"fear":0.004,"happiness":0.0,"neutral":0.95,"sadness":0.018,"surprise":0.027}},"checkinEmo":"surprise","checkinImageCrop":"2020-08-26-3-101743400-crop.jpg","camerain":3,"checkout":"15:57","checkoutEmotion":{"gender":"male","age":35.0,"emotion":{"anger":0.0,"contempt":0.001,"disgust":0.0,"fear":0.0,"happiness":0.025,"neutral":0.972,"sadness":0.002,"surprise":0.0}},"checkoutEmo":"happiness","checkoutImageCrop":"2020-08-26-4-155704560-crop.jpg","cameraout":4,"checkoutdatetime":"20200826155704"}
{"_id":{"$oid":"5f45e1f3ae80396a4edf98d2"},"id":"2522200","checkin":"11:15","checkindatetime":"20200826111543","checkinEmotion":{"gender":"female","age":29.0,"emotion":{"anger":0.0,"contempt":0.0,"disgust":0.0,"fear":0.0,"happiness":0.0,"neutral":0.963,"sadness":0.037,"surprise":0.0}},"checkinEmo":"sadness","checkinImageCrop":"2020-08-26-3-111543200-crop.jpg","camerain":3,"checkout":"17:50","checkoutEmotion":{"gender":"female","age":26,"emotion":{"anger":0,"contempt":0,"disgust":0,"fear":0,"happiness":0,"neutral":1,"sadness":0,"surprise":0}},"checkoutEmo":"neutral","checkoutImageCrop":"2020-08-26-4-175041440-crop.jpg","cameraout":4,"checkoutdatetime":"20200826175041"}
{"_id":{"$oid":"5f45e479ae80396a4edfa947"},"id":"2515908","checkin":"11:26","checkindatetime":"20200826112629","checkinEmotion":{"gender":"female","age":30.0,"emotion":{"anger":0.0,"contempt":0.002,"disgust":0.0,"fear":0.0,"happiness":0.0,"neutral":0.97,"sadness":0.019,"surprise":0.008}},"checkinEmo":"sadness","checkinImageCrop":"2020-08-26-3-112629400-crop.jpg","camerain":3,"checkout":"","checkoutEmotion":{"gender":"","age":0},"checkoutEmo":"","checkoutImageCrop":"","cameraout":0,"checkoutdatetime":""}
{"_id":{"$oid":"5f45ea96ae80396a4edfd31d"},"id":"2515326","checkin":"11:52","checkindatetime":"20200826115234","checkinEmotion":{"gender":"female","age":45.0,"emotion":{"anger":0.0,"contempt":0.001,"disgust":0.0,"fear":0.0,"happiness":0.026,"neutral":0.972,"sadness":0.001,"surprise":0.0}},"checkinEmo":"happiness","checkinImageCrop":"2020-08-26-3-11523400-crop.jpg","camerain":3,"checkout":"17:24","checkoutEmotion":{"gender":"female","age":48.0,"emotion":{"anger":0.0,"contempt":0.001,"disgust":0.001,"fear":0.0,"happiness":0.058,"neutral":0.912,"sadness":0.024,"surprise":0.003}},"checkoutEmo":"happiness","checkoutImageCrop":"2020-08-26-2-172418320-crop.jpg","cameraout":2,"checkoutdatetime":"20200826172418"}
{"_id":{"$oid":"5f46397fae80396a4ee340f8"},"id":"1917128","checkin":"17:29","checkindatetime":"20200826172913","checkinEmotion":{"gender":"female","age":48,"emotion":{"anger":0,"contempt":0,"disgust":0,"fear":0,"happiness":0,"neutral":1,"sadness":0,"surprise":0}},"checkinEmo":"neutral","checkinImageCrop":"2020-08-26-3-172913200-crop.jpg","camerain":3,"checkout":"","checkoutEmotion":{"gender":"","age":0},"checkoutEmo":"","checkoutImageCrop":"","cameraout":0,"checkoutdatetime":""}
